flywheel_extras/__init__.py
flywheel_extras/collector.py
flywheel_extras/deprecated.py
flywheel_extras/instance.py
flywheel_extras/overload.py
flywheel_extras/protocol.py
flywheel_extras/typing.py
flywheel_extras/utils.py
flywheel_fncollector-0.4.0.dist-info/METADATA
flywheel_fncollector-0.4.0.dist-info/WHEEL
flywheel_fncollector-0.4.0.dist-info/entry_points.txt
flywheel_fncollector-0.4.0.dist-info/RECORD
