Metadata-Version: 2.1
Name: flywheel-fncollector
Version: 0.4.0
Summary: Add a FnCollector for Ryanvk Flywheel
Author-Email: F_Qilin <fzq0003@gmail.com>
License: MIT
Classifier: Programming Language :: Python :: 3
Classifier: License :: OSI Approved :: MIT License
Classifier: Operating System :: OS Independent
Classifier: Development Status :: 1 - Planning
Project-URL: Homepage, https://github.com/FZQ0003/Flywheel-FnCollector
Project-URL: Issues, https://github.com/FZQ0003/Flywheel-FnCollector/issues
Requires-Python: >=3.9
Requires-Dist: elaina-flywheel<0.7.0,>=0.6.0
